gosu/.coveragerc_django
gosu/.coveragerc_python
gosu/.flake8
gosu/__init__.py
gosu/main.py
gosu/ansible/setup.yaml
gosu/cmds/__init__.py
gosu/cmds/ansible.py
gosu/cmds/ci.py
gosu/cmds/django.py
gosu/cmds/python.py
gosu-1.1.24.dist-info/entry_points.txt
gosu-1.1.24.dist-info/LICENSE
gosu-1.1.24.dist-info/WHEEL
gosu-1.1.24.dist-info/METADATA
gosu-1.1.24.dist-info/RECORD
